<annotation>
	<folder />
	<filename>image_95.jpg</filename>
	<path>image_95.jpg</path>
	<source>
		<database>roboflow.com</database>
	</source>
	<size>
		<width>1024</width>
		<height>768</height>
		<depth>3</depth>
	</size>
	<segmented>0</segmented>
	<object>
		<name>table</name>
		<pose>Unspecified</pose>
		<truncated>0</truncated>
		<difficult>0</difficult>
		<occluded>0</occluded>
		<bndbox>
			<xmin>59</xmin>
			<xmax>664</xmax>
			<ymin>32</ymin>
			<ymax>756</ymax>
		</bndbox>
		<polygon>
			<x1>58</x1>
			<y1>74</y1>
			<x2>379</x2>
			<y2>31</y2>
			<x3>663</x3>
			<y3>172</y3>
			<x4>619</x4>
			<y4>594</y4>
			<x5>257</x5>
			<y5>755</y5>
			<x6>81</x6>
			<y6>433</y6>
		</polygon>
	</object>
	<object>
		<name>table</name>
		<pose>Unspecified</pose>
		<truncated>0</truncated>
		<difficult>0</difficult>
		<occluded>0</occluded>
		<bndbox>
			<xmin>414</xmin>
			<xmax>936</xmax>
			<ymin>1</ymin>
			<ymax>570</ymax>
		</bndbox>
	</object>
	<metadata>
		<tags>
			<tag>table</tag>
		</tags>
	</metadata>
</annotation>